GUISpices/DragBar.py
GUISpices/Explorer.py
GUISpices/Tray.py
GUISpices/UIWindow.py
GUISpices/Utility.py
GUISpices/__init__.py
GUISpices-1.2.0.dist-info/LICENSE
GUISpices-1.2.0.dist-info/METADATA
GUISpices-1.2.0.dist-info/WHEEL
GUISpices-1.2.0.dist-info/top_level.txt
GUISpices-1.2.0.dist-info/RECORD
