Metadata-Version: 2.1
Name: GUISpices
Version: 1.2.0
Summary: A wrapper module for various GUI usages
Home-page: UNKNOWN
Author: Leon Wiesen
License: UNKNOWN
Platform: UNKNOWN
Classifier: Programming Language :: Python :: 3
Classifier: License :: OSI Approved :: MIT License
Classifier: Operating System :: OS Independent
Requires-Python: >=3.5
Requires-Dist: PySide2
